scrawl/LXGWWenKai-Medium.ttf
scrawl/__init__.py
scrawl/cat1.svg
scrawl/cat2.svg
scrawl/engine.py
scrawl/tools.py
scrawl/wqy-zenhei.ttf
scrawl/pygameGUI/__init__.py
scrawl/pygameGUI/error.py
scrawl/pygameGUI/group.py
scrawl/pygameGUI/composites/entry.py
scrawl/pygameGUI/composites/scrollbar.py
scrawl/pygameGUI/composites/window.py
scrawl/pygameGUI/effects/player.py
scrawl/pygameGUI/widgets/button.py
scrawl/pygameGUI/widgets/frame.py
scrawl/pygameGUI/widgets/label.py
scrawl/pygameGUI/widgets/message.py
scrawl/pygameGUI/widgets/slider.py
scrawl/pygameGUI/widgets/switch.py
scrawl/pygameGUI/widgets/widget.py
scrawl_engine-0.13.3.dist-info/licenses/LICENSE
scrawl_engine-0.13.3.dist-info/METADATA
scrawl_engine-0.13.3.dist-info/WHEEL
scrawl_engine-0.13.3.dist-info/top_level.txt
scrawl_engine-0.13.3.dist-info/RECORD
