Metadata-Version: 2.4
Name: scrawl_engine
Version: 0.13.3
Summary: Write game like Scratch
Home-page: http://github.com/streetartist/scrawl
Author: Streetartist
Author-email: 207148178@qq.com
Keywords: game,engine
Requires-Python: >=3
License-File: LICENSE
Requires-Dist: pygame-ce
Requires-Dist: requests
Requires-Dist: numpy
Requires-Dist: psutil
Requires-Dist: PySide6>=6.6.0
Requires-Dist: QScintilla>=2.14.0
Requires-Dist: markdown>=3.5.0
Requires-Dist: scrawl-engine>=0.13.2
Dynamic: author
Dynamic: author-email
Dynamic: description
Dynamic: description-content-type
Dynamic: home-page
Dynamic: keywords
Dynamic: license-file
Dynamic: requires-dist
Dynamic: requires-python
Dynamic: summary
